block-kriging/__init__.py
block-kriging/cancer_data.gpkg
download/__init__.py
download/air_quality/PL.py
download/air_quality/__init__.py
point-kriging/__init__.py
point-kriging/csv/pl_dem.csv
point-kriging/csv/meuse/README.md
point-kriging/csv/meuse/meuse.csv
point-kriging/csv/meuse/meuse_grid.csv
point-kriging/numpy/armstrong_data.npy
point-kriging/txt/pl_dem.txt
point-kriging/txt/pl_dem_epsg2180.txt
point-kriging/txt/transform.ipynb
pyinterpolate_datasets-2023.0.0.dist-info/METADATA
pyinterpolate_datasets-2023.0.0.dist-info/WHEEL
pyinterpolate_datasets-2023.0.0.dist-info/top_level.txt
pyinterpolate_datasets-2023.0.0.dist-info/RECORD
