Metadata-Version: 2.1
Name: pyinterpolate-datasets
Version: 2023.0.0
Summary: Static datasets and data download scripts for pyinterpolate package
Author-email: Szymon Moliński <simon@dataverselabs.com>
License: BSD-3-Clause
Keywords: pyinterpolate,geostatistics,spatial statistics,kriging,data
Classifier: Development Status :: 2 - Pre-Alpha
Classifier: Intended Audience :: Science/Research
Classifier: Topic :: Scientific/Engineering :: GIS
Classifier: License :: OSI Approved :: BSD License
Classifier: Programming Language :: Python :: 3.8
Classifier: Programming Language :: Python :: 3.9
Classifier: Programming Language :: Python :: 3.10
Classifier: Programming Language :: Python :: 3.11
Requires-Python: >=3.8
Requires-Dist: geopandas
Requires-Dist: requests
Requires-Dist: pandas
Requires-Dist: numpy
Requires-Dist: pydantic
